imhr/__init__.py
imhr/_version.py
imhr/settings.py
imhr/Webgazer/__init__.py
imhr/Webgazer/classify.py
imhr/Webgazer/download.py
imhr/Webgazer/metadata.py
imhr/Webgazer/model.py
imhr/Webgazer/nslr_hmm.py
imhr/Webgazer/plot.py
imhr/Webgazer/processing.py
imhr/Webgazer/raw.py
imhr/Webgazer/redcap.py
imhr/Webgazer/settings.py
imhr/data/__init__.py
imhr/data/download.py
imhr/data/plot.py
imhr/dist/metadata.xlsx
imhr/dist/pytest_requirements.txt
imhr/dist/requirements.txt
imhr/dist/R/.Rhistory
imhr/dist/R/analysis.R
imhr/dist/R/bias.R
imhr/dist/R/bias_behavioral.R
imhr/dist/R/bias_eyetracking.R
imhr/dist/R/bias_summary.pdf
imhr/dist/R/bias_summary_report.pdf
imhr/dist/R/factor_analysis.pdf
imhr/dist/R/old/_summarize_bias.R
imhr/dist/audio/error.wav
imhr/dist/audio/qbeep.wav
imhr/dist/audio/type.wav
imhr/dist/haarcascade/haarcascade_eye.xml
imhr/dist/haarcascade/haarcascade_eye_tree_eyeglasses.xml
imhr/dist/haarcascade/haarcascade_frontalcatface.xml
imhr/dist/haarcascade/haarcascade_frontalcatface_extended.xml
imhr/dist/haarcascade/haarcascade_frontalface_alt.xml
imhr/dist/haarcascade/haarcascade_frontalface_alt2.xml
imhr/dist/haarcascade/haarcascade_frontalface_alt_tree.xml
imhr/dist/haarcascade/haarcascade_frontalface_default.xml
imhr/dist/haarcascade/haarcascade_fullbody.xml
imhr/dist/haarcascade/haarcascade_lefteye_2splits.xml
imhr/dist/haarcascade/haarcascade_licence_plate_rus_16stages.xml
imhr/dist/haarcascade/haarcascade_lowerbody.xml
imhr/dist/haarcascade/haarcascade_profileface.xml
imhr/dist/haarcascade/haarcascade_righteye_2splits.xml
imhr/dist/haarcascade/haarcascade_russian_plate_number.xml
imhr/dist/haarcascade/haarcascade_smile.xml
imhr/dist/haarcascade/haarcascade_upperbody.xml
imhr/dist/r33/definitions.xlsx
imhr/dist/resources/Helvetica.ttf
imhr/dist/resources/nyas12705-sup-0001-text.docx
imhr/dist/resources/pylink_3.4-3.6_win.zip
imhr/dist/resources/pylink_3.6_MacOSX_x64.zip
imhr/dist/roi/classifiers.yaml
imhr/dist/roi/example/2550_RGB.png
imhr-0.3.37.dist-info/LICENSE
imhr-0.3.37.dist-info/METADATA
imhr-0.3.37.dist-info/WHEEL
imhr-0.3.37.dist-info/top_level.txt
imhr-0.3.37.dist-info/RECORD
