Metadata-Version: 2.1
Name: imhr
Version: 0.3.37
Summary: imhr: psychology and data science suite.
Home-page: http://mdl.psy.utexas.edu/a/imhr
Author: Semeon Risom
Author-email: semeon.risom@gmail.com
Maintainer: Semeon Risom
Maintainer-email: semeon.risom@gmail.com
License: MIT
Download-URL: https://github.com/risoms/imhr/
Platform: Darwin
Platform: Windows
Classifier: Intended Audience :: Science/Research
Classifier: Programming Language :: Python :: 3.6
Classifier: Programming Language :: Python :: 3.7
Classifier: License :: OSI Approved :: MIT License
Classifier: Topic :: Scientific/Engineering
Classifier: Topic :: Scientific/Engineering :: Visualization
Classifier: Topic :: Scientific/Engineering :: Human Machine Interfaces
Classifier: Topic :: Multimedia :: Graphics
Classifier: Operating System :: MacOS
Classifier: Operating System :: Microsoft :: Windows
Requires-Python: ~=3.6
Requires-Dist: yarg (>=0.1.9)
Requires-Dist: opencv-python (>=4.1.0.25)
Requires-Dist: bokeh (>=1.2.0)
Requires-Dist: paramiko (>=2.4.2)
Requires-Dist: openpyxl (>=2.6.2)
Requires-Dist: requests (>=2.21.0)
Requires-Dist: setuptools (>=41.0.1)
Requires-Dist: scipy (>=1.3.0)
Requires-Dist: pandas (>=0.24.2)
Requires-Dist: psd-tools (>=1.8.16)
Requires-Dist: docopt (>=0.6.2)
Requires-Dist: numpy (>=1.16.4)
Requires-Dist: seaborn (>=0.9.0)
Requires-Dist: matplotlib (>=3.1.0)
Requires-Dist: Pillow (>=6.0.0)
Requires-Dist: nslr (>=0.0.5)
Requires-Dist: pytest (>=4.5.0)
Requires-Dist: scikit-learn (>=0.21.2)
Requires-Dist: pyobjc ; sys_platform == "darwin"
Requires-Dist: certifi ; sys_platform == "darwin"
Requires-Dist: win32api ; sys_platform == "pywin32"
